Metadata-Version: 2.1
Name: EasyTexto
Version: 0.4
Summary: Paquete para manejar archivos de texto de forma sencilla
Home-page: https://github.com/nakato156/EasyTexto
Author: Christian (Nakato)
Author-email: christianvelasces@gmail.com
License: MIT
Keywords: file,files,text
Platform: UNKNOWN
